flask_gssapi.py
Flask_GSSAPI-1.5.0.dist-info/LICENSE
Flask_GSSAPI-1.5.0.dist-info/METADATA
Flask_GSSAPI-1.5.0.dist-info/WHEEL
Flask_GSSAPI-1.5.0.dist-info/top_level.txt
Flask_GSSAPI-1.5.0.dist-info/RECORD
