Metadata-Version: 2.1
Name: Flask-GSSAPI
Version: 1.5.0
Summary: HTTP Negotiate (GSSAPI) authentication support for Flask applications.
Home-page: https://github.com/cour4g3/flask-gssapi
Author: Michael de Villiers
Author-email: michael@cour4g3.me
License: MIT
Platform: any
Classifier: Environment :: Web Environment
Classifier: Intended Audience :: Developers
Classifier: License :: OSI Approved :: MIT License
Classifier: Operating System :: OS Independent
Classifier: Programming Language :: Python :: 2.6
Classifier: Programming Language :: Python :: 2.7
Classifier: Programming Language :: Python :: 3.3
Classifier: Programming Language :: Python :: 3.4
Classifier: Programming Language :: Python :: 3.5
Classifier: Topic :: Internet :: WWW/HTTP :: Dynamic Content
Classifier: Topic :: Software Development :: Libraries :: Python Modules
Requires-Dist: flask
Requires-Dist: gssapi
